{
  "changelog": [
    {
      "ChangeList": [
        {
          "Id": "0f0e1863-9ec9-4914-9c41-648ed3c8ca1d",
          "ApiChange": "EnumType",
          "ChangedApiName": "mobileAppRelationshipType",
          "ChangeType": "Addition",
          "Description": "Added the [mobileAppRelationshipType](/?view=graph-rest-beta) resource *@\u0026*",
          "Target": "mobileAppRelationshipType"
        },
        {
          "Id": "0f0e1863-9ec9-4914-9c41-648ed3c8ca1d",
          "ApiChange": "EnumType",
          "ChangedApiName": "mobileAppSupersedenceType",
          "ChangeType": "Addition",
          "Description": "Added the [mobileAppSupersedenceType](/?view=graph-rest-beta) resource *@\u0026*",
          "Target": "mobileAppSupersedenceType"
        },
        {
          "Id": "0f0e1863-9ec9-4914-9c41-648ed3c8ca1d",
          "ApiChange": "EntityType",
          "ChangedApiName": "deviceManagement",
          "ChangeType": "Addition",
          "Description": "Added the [deviceManagement](/graph/api/resources/intune-deviceManagement?view=graph-rest-beta) resource *@\u0026*",
          "Target": "deviceManagement"
        },
        {
          "Id": "0f0e1863-9ec9-4914-9c41-648ed3c8ca1d",
          "ApiChange": "EntityType",
          "ChangedApiName": "deviceManagementReports",
          "ChangeType": "Addition",
          "Description": "Added the [deviceManagementReports](/graph/api/resources/intune-deviceManagementReports?view=graph-rest-beta) resource *@\u0026*",
          "Target": "deviceManagementReports"
        },
        {
          "Id": "0f0e1863-9ec9-4914-9c41-648ed3c8ca1d",
          "ApiChange": "Property",
          "ChangedApiName": "supersededAppCount",
          "ChangeType": "Addition",
          "Description": "Added the **supersededAppCount** property to [mobileApp](/?view=graph-rest-beta) resource",
          "Target": "mobileApp"
        },
        {
          "Id": "0f0e1863-9ec9-4914-9c41-648ed3c8ca1d",
          "ApiChange": "Property",
          "ChangedApiName": "supersedingAppCount",
          "ChangeType": "Addition",
          "Description": "Added the **supersedingAppCount** property to [mobileApp](/?view=graph-rest-beta) resource",
          "Target": "mobileApp"
        },
        {
          "Id": "0f0e1863-9ec9-4914-9c41-648ed3c8ca1d",
          "ApiChange": "Property",
          "ChangedApiName": "uploadState",
          "ChangeType": "Change",
          "Description": "Changed the type of the **uploadState** property in the [mobileApp](/?view=graph-rest-beta) resource",
          "Target": "mobileApp"
        },
        {
          "Id": "0f0e1863-9ec9-4914-9c41-648ed3c8ca1d",
          "ApiChange": "NavigationProperty",
          "ChangedApiName": "relationships",
          "ChangeType": "Change",
          "Description": "Removed the **relationships** relationship from [mobileApp](/?view=graph-rest-beta) resource",
          "Target": "mobileApp"
        },
        {
          "Id": "0f0e1863-9ec9-4914-9c41-648ed3c8ca1d",
          "ApiChange": "Property",
          "ChangedApiName": "targetType",
          "ChangeType": "Addition",
          "Description": "Added the **targetType** property to [mobileAppRelationship](/?view=graph-rest-beta) resource",
          "Target": "mobileAppRelationship"
        },
        {
          "Id": "0f0e1863-9ec9-4914-9c41-648ed3c8ca1d",
          "ApiChange": "EntityType",
          "ChangedApiName": "mobileAppSupersedence",
          "ChangeType": "Addition",
          "Description": "Added the [mobileAppSupersedence](/graph/api/resources/intune-mobileAppSupersedence?view=graph-rest-beta) resource *@\u0026*",
          "Target": "mobileAppSupersedence"
        },
        {
          "Id": "0f0e1863-9ec9-4914-9c41-648ed3c8ca1d",
          "ApiChange": "Property",
          "ChangedApiName": "installLanguage",
          "ChangeType": "Deletion",
          "Description": "Removed the **installLanguage** property from [win32LobApp](/?view=graph-rest-beta) resource",
          "Target": "win32LobApp"
        },
        {
          "Id": "0f0e1863-9ec9-4914-9c41-648ed3c8ca1d",
          "ApiChange": "Action",
          "ChangedApiName": "getAppsInstallSummaryReport",
          "ChangeType": "Addition",
          "Description": "Added the [getAppsInstallSummaryReport](/graph/api/intune-getAppsInstallSummaryReport-getAppsInstallSummaryReport?view=graph-rest-beta) method to the [getAppsInstallSummaryReport](/graph/api/intune-getAppsInstallSummaryReport-getAppsInstallSummaryReport?view=graph-rest-beta) resource",
          "Target": "getAppsInstallSummaryReport"
        },
        {
          "Id": "0f0e1863-9ec9-4914-9c41-648ed3c8ca1d",
          "ApiChange": "Action",
          "ChangedApiName": "getAppStatusOverviewReport",
          "ChangeType": "Addition",
          "Description": "Added the [getAppStatusOverviewReport](/graph/api/intune-getAppStatusOverviewReport-getAppStatusOverviewReport?view=graph-rest-beta) method to the [getAppStatusOverviewReport](/graph/api/intune-getAppStatusOverviewReport-getAppStatusOverviewReport?view=graph-rest-beta) resource",
          "Target": "getAppStatusOverviewReport"
        },
        {
          "Id": "0f0e1863-9ec9-4914-9c41-648ed3c8ca1d",
          "ApiChange": "Action",
          "ChangedApiName": "getDeviceInstallStatusReport",
          "ChangeType": "Addition",
          "Description": "Added the [getDeviceInstallStatusReport](/graph/api/intune-getDeviceInstallStatusReport-getDeviceInstallStatusReport?view=graph-rest-beta) method to the [getDeviceInstallStatusReport](/graph/api/intune-getDeviceInstallStatusReport-getDeviceInstallStatusReport?view=graph-rest-beta) resource",
          "Target": "getDeviceInstallStatusReport"
        },
        {
          "Id": "0f0e1863-9ec9-4914-9c41-648ed3c8ca1d",
          "ApiChange": "Action",
          "ChangedApiName": "getUserInstallStatusReport",
          "ChangeType": "Addition",
          "Description": "Added the [getUserInstallStatusReport](/graph/api/intune-getUserInstallStatusReport-getUserInstallStatusReport?view=graph-rest-beta) method to the [getUserInstallStatusReport](/graph/api/intune-getUserInstallStatusReport-getUserInstallStatusReport?view=graph-rest-beta) resource",
          "Target": "getUserInstallStatusReport"
        },
        {
          "Id": "0f0e1863-9ec9-4914-9c41-648ed3c8ca1d",
          "ApiChange": "EntityContainer",
          "ChangedApiName": "edm_50200622",
          "ChangeType": "Deletion",
          "Description": "Removed the **edm_50200622** resource type *@\u0026*",
          "Target": "edm_50200622"
        },
        {
          "Id": "0f0e1863-9ec9-4914-9c41-648ed3c8ca1d",
          "ApiChange": "EntityContainer",
          "ChangedApiName": "edm_50200902",
          "ChangeType": "Addition",
          "Description": "Added the [edm_50200902](/?view=graph-rest-beta) resource *@\u0026*",
          "Target": "edm_50200902"
        }
      ],
      "Id": "0f0e1863-9ec9-4914-9c41-648ed3c8ca1d",
      "Cloud": "Fairfax",
      "Version": "beta",
      "CreatedDateTime": "2020-10-12T16:12:16.0580178Z",
      "WorkloadArea": "Microsoft.Intune.Applications",
      "SubArea": "Corporate management"
    },
    {
      "ChangeList": [
        {
          "Id": "7912407e-1762-41b1-943d-7e04c9612780",
          "ApiChange": "EnumType",
          "ChangedApiName": "mobileAppRelationshipType",
          "ChangeType": "Addition",
          "Description": "Added the [mobileAppRelationshipType](/?view=graph-rest-beta) resource *@\u0026*",
          "Target": "mobileAppRelationshipType"
        },
        {
          "Id": "7912407e-1762-41b1-943d-7e04c9612780",
          "ApiChange": "EnumType",
          "ChangedApiName": "mobileAppSupersedenceType",
          "ChangeType": "Addition",
          "Description": "Added the [mobileAppSupersedenceType](/?view=graph-rest-beta) resource *@\u0026*",
          "Target": "mobileAppSupersedenceType"
        },
        {
          "Id": "7912407e-1762-41b1-943d-7e04c9612780",
          "ApiChange": "EntityType",
          "ChangedApiName": "deviceManagement",
          "ChangeType": "Addition",
          "Description": "Added the [deviceManagement](/graph/api/resources/intune-deviceManagement?view=graph-rest-beta) resource *@\u0026*",
          "Target": "deviceManagement"
        },
        {
          "Id": "7912407e-1762-41b1-943d-7e04c9612780",
          "ApiChange": "EntityType",
          "ChangedApiName": "deviceManagementReports",
          "ChangeType": "Addition",
          "Description": "Added the [deviceManagementReports](/graph/api/resources/intune-deviceManagementReports?view=graph-rest-beta) resource *@\u0026*",
          "Target": "deviceManagementReports"
        },
        {
          "Id": "7912407e-1762-41b1-943d-7e04c9612780",
          "ApiChange": "Property",
          "ChangedApiName": "supersededAppCount",
          "ChangeType": "Addition",
          "Description": "Added the **supersededAppCount** property to [mobileApp](/?view=graph-rest-beta) resource",
          "Target": "mobileApp"
        },
        {
          "Id": "7912407e-1762-41b1-943d-7e04c9612780",
          "ApiChange": "Property",
          "ChangedApiName": "supersedingAppCount",
          "ChangeType": "Addition",
          "Description": "Added the **supersedingAppCount** property to [mobileApp](/?view=graph-rest-beta) resource",
          "Target": "mobileApp"
        },
        {
          "Id": "7912407e-1762-41b1-943d-7e04c9612780",
          "ApiChange": "Property",
          "ChangedApiName": "uploadState",
          "ChangeType": "Change",
          "Description": "Changed the type of the **uploadState** property in the [mobileApp](/?view=graph-rest-beta) resource",
          "Target": "mobileApp"
        },
        {
          "Id": "7912407e-1762-41b1-943d-7e04c9612780",
          "ApiChange": "NavigationProperty",
          "ChangedApiName": "relationships",
          "ChangeType": "Change",
          "Description": "Removed the **relationships** relationship from [mobileApp](/?view=graph-rest-beta) resource",
          "Target": "mobileApp"
        },
        {
          "Id": "7912407e-1762-41b1-943d-7e04c9612780",
          "ApiChange": "Property",
          "ChangedApiName": "targetType",
          "ChangeType": "Addition",
          "Description": "Added the **targetType** property to [mobileAppRelationship](/?view=graph-rest-beta) resource",
          "Target": "mobileAppRelationship"
        },
        {
          "Id": "7912407e-1762-41b1-943d-7e04c9612780",
          "ApiChange": "EntityType",
          "ChangedApiName": "mobileAppSupersedence",
          "ChangeType": "Addition",
          "Description": "Added the [mobileAppSupersedence](/graph/api/resources/intune-mobileAppSupersedence?view=graph-rest-beta) resource *@\u0026*",
          "Target": "mobileAppSupersedence"
        },
        {
          "Id": "7912407e-1762-41b1-943d-7e04c9612780",
          "ApiChange": "Property",
          "ChangedApiName": "installLanguage",
          "ChangeType": "Deletion",
          "Description": "Removed the **installLanguage** property from [win32LobApp](/?view=graph-rest-beta) resource",
          "Target": "win32LobApp"
        },
        {
          "Id": "7912407e-1762-41b1-943d-7e04c9612780",
          "ApiChange": "Action",
          "ChangedApiName": "getAppsInstallSummaryReport",
          "ChangeType": "Addition",
          "Description": "Added the [getAppsInstallSummaryReport](/graph/api/intune-getAppsInstallSummaryReport-getAppsInstallSummaryReport?view=graph-rest-beta) method to the [getAppsInstallSummaryReport](/graph/api/intune-getAppsInstallSummaryReport-getAppsInstallSummaryReport?view=graph-rest-beta) resource",
          "Target": "getAppsInstallSummaryReport"
        },
        {
          "Id": "7912407e-1762-41b1-943d-7e04c9612780",
          "ApiChange": "Action",
          "ChangedApiName": "getAppStatusOverviewReport",
          "ChangeType": "Addition",
          "Description": "Added the [getAppStatusOverviewReport](/graph/api/intune-getAppStatusOverviewReport-getAppStatusOverviewReport?view=graph-rest-beta) method to the [getAppStatusOverviewReport](/graph/api/intune-getAppStatusOverviewReport-getAppStatusOverviewReport?view=graph-rest-beta) resource",
          "Target": "getAppStatusOverviewReport"
        },
        {
          "Id": "7912407e-1762-41b1-943d-7e04c9612780",
          "ApiChange": "Action",
          "ChangedApiName": "getDeviceInstallStatusReport",
          "ChangeType": "Addition",
          "Description": "Added the [getDeviceInstallStatusReport](/graph/api/intune-getDeviceInstallStatusReport-getDeviceInstallStatusReport?view=graph-rest-beta) method to the [getDeviceInstallStatusReport](/graph/api/intune-getDeviceInstallStatusReport-getDeviceInstallStatusReport?view=graph-rest-beta) resource",
          "Target": "getDeviceInstallStatusReport"
        },
        {
          "Id": "7912407e-1762-41b1-943d-7e04c9612780",
          "ApiChange": "Action",
          "ChangedApiName": "getUserInstallStatusReport",
          "ChangeType": "Addition",
          "Description": "Added the [getUserInstallStatusReport](/graph/api/intune-getUserInstallStatusReport-getUserInstallStatusReport?view=graph-rest-beta) method to the [getUserInstallStatusReport](/graph/api/intune-getUserInstallStatusReport-getUserInstallStatusReport?view=graph-rest-beta) resource",
          "Target": "getUserInstallStatusReport"
        },
        {
          "Id": "7912407e-1762-41b1-943d-7e04c9612780",
          "ApiChange": "EntityContainer",
          "ChangedApiName": "edm_50200622",
          "ChangeType": "Deletion",
          "Description": "Removed the **edm_50200622** resource type *@\u0026*",
          "Target": "edm_50200622"
        },
        {
          "Id": "7912407e-1762-41b1-943d-7e04c9612780",
          "ApiChange": "EntityContainer",
          "ChangedApiName": "edm_50200902",
          "ChangeType": "Addition",
          "Description": "Added the [edm_50200902](/?view=graph-rest-beta) resource *@\u0026*",
          "Target": "edm_50200902"
        }
      ],
      "Id": "7912407e-1762-41b1-943d-7e04c9612780",
      "Cloud": "Mooncake",
      "Version": "beta",
      "CreatedDateTime": "2020-10-12T16:12:16.0580206Z",
      "WorkloadArea": "Microsoft.Intune.Applications",
      "SubArea": "Corporate management"
    },
    {
      "ChangeList": [
        {
          "Id": "b5f414c6-8745-4ea2-a569-2f38ace22df3",
          "ApiChange": "EnumType",
          "ChangedApiName": "mobileAppRelationshipType",
          "ChangeType": "Addition",
          "Description": "Added the [mobileAppRelationshipType](/?view=graph-rest-beta) resource *@\u0026*",
          "Target": "mobileAppRelationshipType"
        },
        {
          "Id": "b5f414c6-8745-4ea2-a569-2f38ace22df3",
          "ApiChange": "EnumType",
          "ChangedApiName": "mobileAppSupersedenceType",
          "ChangeType": "Addition",
          "Description": "Added the [mobileAppSupersedenceType](/?view=graph-rest-beta) resource *@\u0026*",
          "Target": "mobileAppSupersedenceType"
        },
        {
          "Id": "b5f414c6-8745-4ea2-a569-2f38ace22df3",
          "ApiChange": "EntityType",
          "ChangedApiName": "deviceManagement",
          "ChangeType": "Addition",
          "Description": "Added the [deviceManagement](/graph/api/resources/intune-deviceManagement?view=graph-rest-beta) resource *@\u0026*",
          "Target": "deviceManagement"
        },
        {
          "Id": "b5f414c6-8745-4ea2-a569-2f38ace22df3",
          "ApiChange": "EntityType",
          "ChangedApiName": "deviceManagementReports",
          "ChangeType": "Addition",
          "Description": "Added the [deviceManagementReports](/graph/api/resources/intune-deviceManagementReports?view=graph-rest-beta) resource *@\u0026*",
          "Target": "deviceManagementReports"
        },
        {
          "Id": "b5f414c6-8745-4ea2-a569-2f38ace22df3",
          "ApiChange": "Property",
          "ChangedApiName": "supersededAppCount",
          "ChangeType": "Addition",
          "Description": "Added the **supersededAppCount** property to [mobileApp](/?view=graph-rest-beta) resource",
          "Target": "mobileApp"
        },
        {
          "Id": "b5f414c6-8745-4ea2-a569-2f38ace22df3",
          "ApiChange": "Property",
          "ChangedApiName": "supersedingAppCount",
          "ChangeType": "Addition",
          "Description": "Added the **supersedingAppCount** property to [mobileApp](/?view=graph-rest-beta) resource",
          "Target": "mobileApp"
        },
        {
          "Id": "b5f414c6-8745-4ea2-a569-2f38ace22df3",
          "ApiChange": "Property",
          "ChangedApiName": "uploadState",
          "ChangeType": "Change",
          "Description": "Changed the type of the **uploadState** property in the [mobileApp](/?view=graph-rest-beta) resource",
          "Target": "mobileApp"
        },
        {
          "Id": "b5f414c6-8745-4ea2-a569-2f38ace22df3",
          "ApiChange": "NavigationProperty",
          "ChangedApiName": "relationships",
          "ChangeType": "Change",
          "Description": "Removed the **relationships** relationship from [mobileApp](/?view=graph-rest-beta) resource",
          "Target": "mobileApp"
        },
        {
          "Id": "b5f414c6-8745-4ea2-a569-2f38ace22df3",
          "ApiChange": "Property",
          "ChangedApiName": "targetType",
          "ChangeType": "Addition",
          "Description": "Added the **targetType** property to [mobileAppRelationship](/?view=graph-rest-beta) resource",
          "Target": "mobileAppRelationship"
        },
        {
          "Id": "b5f414c6-8745-4ea2-a569-2f38ace22df3",
          "ApiChange": "EntityType",
          "ChangedApiName": "mobileAppSupersedence",
          "ChangeType": "Addition",
          "Description": "Added the [mobileAppSupersedence](/graph/api/resources/intune-mobileAppSupersedence?view=graph-rest-beta) resource *@\u0026*",
          "Target": "mobileAppSupersedence"
        },
        {
          "Id": "b5f414c6-8745-4ea2-a569-2f38ace22df3",
          "ApiChange": "Property",
          "ChangedApiName": "installLanguage",
          "ChangeType": "Deletion",
          "Description": "Removed the **installLanguage** property from [win32LobApp](/?view=graph-rest-beta) resource",
          "Target": "win32LobApp"
        },
        {
          "Id": "b5f414c6-8745-4ea2-a569-2f38ace22df3",
          "ApiChange": "Action",
          "ChangedApiName": "getAppsInstallSummaryReport",
          "ChangeType": "Addition",
          "Description": "Added the [getAppsInstallSummaryReport](/graph/api/intune-getAppsInstallSummaryReport-getAppsInstallSummaryReport?view=graph-rest-beta) method to the [getAppsInstallSummaryReport](/graph/api/intune-getAppsInstallSummaryReport-getAppsInstallSummaryReport?view=graph-rest-beta) resource",
          "Target": "getAppsInstallSummaryReport"
        },
        {
          "Id": "b5f414c6-8745-4ea2-a569-2f38ace22df3",
          "ApiChange": "Action",
          "ChangedApiName": "getAppStatusOverviewReport",
          "ChangeType": "Addition",
          "Description": "Added the [getAppStatusOverviewReport](/graph/api/intune-getAppStatusOverviewReport-getAppStatusOverviewReport?view=graph-rest-beta) method to the [getAppStatusOverviewReport](/graph/api/intune-getAppStatusOverviewReport-getAppStatusOverviewReport?view=graph-rest-beta) resource",
          "Target": "getAppStatusOverviewReport"
        },
        {
          "Id": "b5f414c6-8745-4ea2-a569-2f38ace22df3",
          "ApiChange": "Action",
          "ChangedApiName": "getDeviceInstallStatusReport",
          "ChangeType": "Addition",
          "Description": "Added the [getDeviceInstallStatusReport](/graph/api/intune-getDeviceInstallStatusReport-getDeviceInstallStatusReport?view=graph-rest-beta) method to the [getDeviceInstallStatusReport](/graph/api/intune-getDeviceInstallStatusReport-getDeviceInstallStatusReport?view=graph-rest-beta) resource",
          "Target": "getDeviceInstallStatusReport"
        },
        {
          "Id": "b5f414c6-8745-4ea2-a569-2f38ace22df3",
          "ApiChange": "Action",
          "ChangedApiName": "getUserInstallStatusReport",
          "ChangeType": "Addition",
          "Description": "Added the [getUserInstallStatusReport](/graph/api/intune-getUserInstallStatusReport-getUserInstallStatusReport?view=graph-rest-beta) method to the [getUserInstallStatusReport](/graph/api/intune-getUserInstallStatusReport-getUserInstallStatusReport?view=graph-rest-beta) resource",
          "Target": "getUserInstallStatusReport"
        },
        {
          "Id": "b5f414c6-8745-4ea2-a569-2f38ace22df3",
          "ApiChange": "EntityContainer",
          "ChangedApiName": "edm_50200622",
          "ChangeType": "Deletion",
          "Description": "Removed the **edm_50200622** resource type *@\u0026*",
          "Target": "edm_50200622"
        },
        {
          "Id": "b5f414c6-8745-4ea2-a569-2f38ace22df3",
          "ApiChange": "EntityContainer",
          "ChangedApiName": "edm_50200902",
          "ChangeType": "Addition",
          "Description": "Added the [edm_50200902](/?view=graph-rest-beta) resource *@\u0026*",
          "Target": "edm_50200902"
        }
      ],
      "Id": "b5f414c6-8745-4ea2-a569-2f38ace22df3",
      "Cloud": "Prod",
      "Version": "beta",
      "CreatedDateTime": "2020-10-12T16:12:16.0580235Z",
      "WorkloadArea": "Microsoft.Intune.Applications",
      "SubArea": "Corporate management"
    },
    {
      "ChangeList": [
        {
          "Id": "b139dc05-bdad-4156-bf26-e087c40c0419",
          "ApiChange": "EnumType",
          "ChangedApiName": "runAsAccountType",
          "ChangeType": "Addition",
          "Description": "Added the [runAsAccountType](/?view=graph-rest-1.0) resource *@\u0026*",
          "Target": "runAsAccountType"
        },
        {
          "Id": "b139dc05-bdad-4156-bf26-e087c40c0419",
          "ApiChange": "EnumType",
          "ChangedApiName": "win32LobAppFileSystemOperationType",
          "ChangeType": "Addition",
          "Description": "Added the [win32LobAppFileSystemOperationType](/?view=graph-rest-1.0) resource *@\u0026*",
          "Target": "win32LobAppFileSystemOperationType"
        },
        {
          "Id": "b139dc05-bdad-4156-bf26-e087c40c0419",
          "ApiChange": "EnumType",
          "ChangedApiName": "win32LobAppMsiPackageType",
          "ChangeType": "Addition",
          "Description": "Added the [win32LobAppMsiPackageType](/?view=graph-rest-1.0) resource *@\u0026*",
          "Target": "win32LobAppMsiPackageType"
        },
        {
          "Id": "b139dc05-bdad-4156-bf26-e087c40c0419",
          "ApiChange": "EnumType",
          "ChangedApiName": "win32LobAppNotification",
          "ChangeType": "Addition",
          "Description": "Added the [win32LobAppNotification](/?view=graph-rest-1.0) resource *@\u0026*",
          "Target": "win32LobAppNotification"
        },
        {
          "Id": "b139dc05-bdad-4156-bf26-e087c40c0419",
          "ApiChange": "EnumType",
          "ChangedApiName": "win32LobAppPowerShellScriptRuleOperationType",
          "ChangeType": "Addition",
          "Description": "Added the [win32LobAppPowerShellScriptRuleOperationType](/?view=graph-rest-1.0) resource *@\u0026*",
          "Target": "win32LobAppPowerShellScriptRuleOperationType"
        },
        {
          "Id": "b139dc05-bdad-4156-bf26-e087c40c0419",
          "ApiChange": "EnumType",
          "ChangedApiName": "win32LobAppRegistryRuleOperationType",
          "ChangeType": "Addition",
          "Description": "Added the [win32LobAppRegistryRuleOperationType](/?view=graph-rest-1.0) resource *@\u0026*",
          "Target": "win32LobAppRegistryRuleOperationType"
        },
        {
          "Id": "b139dc05-bdad-4156-bf26-e087c40c0419",
          "ApiChange": "EnumType",
          "ChangedApiName": "win32LobAppRestartBehavior",
          "ChangeType": "Addition",
          "Description": "Added the [win32LobAppRestartBehavior](/?view=graph-rest-1.0) resource *@\u0026*",
          "Target": "win32LobAppRestartBehavior"
        },
        {
          "Id": "b139dc05-bdad-4156-bf26-e087c40c0419",
          "ApiChange": "EnumType",
          "ChangedApiName": "win32LobAppReturnCodeType",
          "ChangeType": "Addition",
          "Description": "Added the [win32LobAppReturnCodeType](/?view=graph-rest-1.0) resource *@\u0026*",
          "Target": "win32LobAppReturnCodeType"
        },
        {
          "Id": "b139dc05-bdad-4156-bf26-e087c40c0419",
          "ApiChange": "EnumType",
          "ChangedApiName": "win32LobAppRuleOperator",
          "ChangeType": "Addition",
          "Description": "Added the [win32LobAppRuleOperator](/?view=graph-rest-1.0) resource *@\u0026*",
          "Target": "win32LobAppRuleOperator"
        },
        {
          "Id": "b139dc05-bdad-4156-bf26-e087c40c0419",
          "ApiChange": "EnumType",
          "ChangedApiName": "win32LobAppRuleType",
          "ChangeType": "Addition",
          "Description": "Added the [win32LobAppRuleType](/?view=graph-rest-1.0) resource *@\u0026*",
          "Target": "win32LobAppRuleType"
        },
        {
          "Id": "b139dc05-bdad-4156-bf26-e087c40c0419",
          "ApiChange": "ComplexType",
          "ChangedApiName": "mobileAppInstallTimeSettings",
          "ChangeType": "Addition",
          "Description": "Added the [mobileAppInstallTimeSettings](/graph/api/resources/intune-mobileAppInstallTimeSettings?view=graph-rest-1.0) resource type",
          "Target": "mobileAppInstallTimeSettings"
        },
        {
          "Id": "b139dc05-bdad-4156-bf26-e087c40c0419",
          "ApiChange": "ComplexType",
          "ChangedApiName": "win32LobAppAssignmentSettings",
          "ChangeType": "Addition",
          "Description": "Added the [win32LobAppAssignmentSettings](/graph/api/resources/intune-win32LobAppAssignmentSettings?view=graph-rest-1.0) resource type",
          "Target": "win32LobAppAssignmentSettings"
        },
        {
          "Id": "b139dc05-bdad-4156-bf26-e087c40c0419",
          "ApiChange": "ComplexType",
          "ChangedApiName": "win32LobAppFileSystemRule",
          "ChangeType": "Addition",
          "Description": "Added the [win32LobAppFileSystemRule](/graph/api/resources/intune-win32LobAppFileSystemRule?view=graph-rest-1.0) resource type",
          "Target": "win32LobAppFileSystemRule"
        },
        {
          "Id": "b139dc05-bdad-4156-bf26-e087c40c0419",
          "ApiChange": "ComplexType",
          "ChangedApiName": "win32LobAppInstallExperience",
          "ChangeType": "Addition",
          "Description": "Added the [win32LobAppInstallExperience](/graph/api/resources/intune-win32LobAppInstallExperience?view=graph-rest-1.0) resource type",
          "Target": "win32LobAppInstallExperience"
        },
        {
          "Id": "b139dc05-bdad-4156-bf26-e087c40c0419",
          "ApiChange": "ComplexType",
          "ChangedApiName": "win32LobAppMsiInformation",
          "ChangeType": "Addition",
          "Description": "Added the [win32LobAppMsiInformation](/graph/api/resources/intune-win32LobAppMsiInformation?view=graph-rest-1.0) resource type",
          "Target": "win32LobAppMsiInformation"
        },
        {
          "Id": "b139dc05-bdad-4156-bf26-e087c40c0419",
          "ApiChange": "ComplexType",
          "ChangedApiName": "win32LobAppPowerShellScriptRule",
          "ChangeType": "Addition",
          "Description": "Added the [win32LobAppPowerShellScriptRule](/graph/api/resources/intune-win32LobAppPowerShellScriptRule?view=graph-rest-1.0) resource type",
          "Target": "win32LobAppPowerShellScriptRule"
        },
        {
          "Id": "b139dc05-bdad-4156-bf26-e087c40c0419",
          "ApiChange": "ComplexType",
          "ChangedApiName": "win32LobAppProductCodeRule",
          "ChangeType": "Addition",
          "Description": "Added the [win32LobAppProductCodeRule](/graph/api/resources/intune-win32LobAppProductCodeRule?view=graph-rest-1.0) resource type",
          "Target": "win32LobAppProductCodeRule"
        },
        {
          "Id": "b139dc05-bdad-4156-bf26-e087c40c0419",
          "ApiChange": "ComplexType",
          "ChangedApiName": "win32LobAppRegistryRule",
          "ChangeType": "Addition",
          "Description": "Added the [win32LobAppRegistryRule](/graph/api/resources/intune-win32LobAppRegistryRule?view=graph-rest-1.0) resource type",
          "Target": "win32LobAppRegistryRule"
        },
        {
          "Id": "b139dc05-bdad-4156-bf26-e087c40c0419",
          "ApiChange": "ComplexType",
          "ChangedApiName": "win32LobAppRestartSettings",
          "ChangeType": "Addition",
          "Description": "Added the [win32LobAppRestartSettings](/graph/api/resources/intune-win32LobAppRestartSettings?view=graph-rest-1.0) resource type",
          "Target": "win32LobAppRestartSettings"
        },
        {
          "Id": "b139dc05-bdad-4156-bf26-e087c40c0419",
          "ApiChange": "ComplexType",
          "ChangedApiName": "win32LobAppReturnCode",
          "ChangeType": "Addition",
          "Description": "Added the [win32LobAppReturnCode](/graph/api/resources/intune-win32LobAppReturnCode?view=graph-rest-1.0) resource type",
          "Target": "win32LobAppReturnCode"
        },
        {
          "Id": "b139dc05-bdad-4156-bf26-e087c40c0419",
          "ApiChange": "ComplexType",
          "ChangedApiName": "win32LobAppRule",
          "ChangeType": "Addition",
          "Description": "Added the [win32LobAppRule](/graph/api/resources/intune-win32LobAppRule?view=graph-rest-1.0) resource type",
          "Target": "win32LobAppRule"
        },
        {
          "Id": "b139dc05-bdad-4156-bf26-e087c40c0419",
          "ApiChange": "EntityType",
          "ChangedApiName": "win32LobApp",
          "ChangeType": "Addition",
          "Description": "Added the [win32LobApp](/graph/api/resources/intune-win32LobApp?view=graph-rest-1.0) resource *@\u0026*",
          "Target": "win32LobApp"
        }
      ],
      "Id": "b139dc05-bdad-4156-bf26-e087c40c0419",
      "Cloud": "Prod",
      "Version": "v1.0",
      "CreatedDateTime": "2020-10-12T16:12:16.0580267Z",
      "WorkloadArea": "Microsoft.Intune.Applications",
      "SubArea": "Corporate management"
    }
  ]
}