{
  "changelog": [
    {
      "ChangeList": [
        {
          "Id": "a7e4a6cf-2393-40d7-bf4c-5b8595ec4ad4",
          "ApiChange": "EnumType",
          "ChangedApiName": "mobileAppRelationshipType",
          "ChangeType": "Addition",
          "Description": "Added the [mobileAppRelationshipType](/?view=graph-rest-beta) resource *@\u0026*",
          "Target": "mobileAppRelationshipType"
        },
        {
          "Id": "a7e4a6cf-2393-40d7-bf4c-5b8595ec4ad4",
          "ApiChange": "EnumType",
          "ChangedApiName": "mobileAppSupersedenceType",
          "ChangeType": "Addition",
          "Description": "Added the [mobileAppSupersedenceType](/?view=graph-rest-beta) resource *@\u0026*",
          "Target": "mobileAppSupersedenceType"
        },
        {
          "Id": "a7e4a6cf-2393-40d7-bf4c-5b8595ec4ad4",
          "ApiChange": "EntityType",
          "ChangedApiName": "deviceManagement",
          "ChangeType": "Addition",
          "Description": "Added the [deviceManagement](/graph/api/resources/intune-deviceManagement?view=graph-rest-beta) resource *@\u0026*",
          "Target": "deviceManagement"
        },
        {
          "Id": "a7e4a6cf-2393-40d7-bf4c-5b8595ec4ad4",
          "ApiChange": "EntityType",
          "ChangedApiName": "deviceManagementReports",
          "ChangeType": "Addition",
          "Description": "Added the [deviceManagementReports](/graph/api/resources/intune-deviceManagementReports?view=graph-rest-beta) resource *@\u0026*",
          "Target": "deviceManagementReports"
        },
        {
          "Id": "a7e4a6cf-2393-40d7-bf4c-5b8595ec4ad4",
          "ApiChange": "EntityType",
          "ChangedApiName": "mobileAppSupersedence",
          "ChangeType": "Addition",
          "Description": "Added the [mobileAppSupersedence](/graph/api/resources/intune-mobileAppSupersedence?view=graph-rest-beta) resource *@\u0026*",
          "Target": "mobileAppSupersedence"
        },
        {
          "Id": "a7e4a6cf-2393-40d7-bf4c-5b8595ec4ad4",
          "ApiChange": "Property",
          "ChangedApiName": "installLanguage",
          "ChangeType": "Deletion",
          "Description": "Removed the **installLanguage** property from [win32LobApp](/?view=graph-rest-beta) resource",
          "Target": "win32LobApp"
        },
        {
          "Id": "a7e4a6cf-2393-40d7-bf4c-5b8595ec4ad4",
          "ApiChange": "NavigationProperty",
          "ChangedApiName": "relationships",
          "ChangeType": "Change",
          "Description": "Removed the **relationships** relationship from [mobileApp](/?view=graph-rest-beta) resource",
          "Target": "mobileApp"
        },
        {
          "Id": "a7e4a6cf-2393-40d7-bf4c-5b8595ec4ad4",
          "ApiChange": "Property",
          "ChangedApiName": "targetType",
          "ChangeType": "Addition",
          "Description": "Added the **targetType** property to [mobileAppRelationship](/?view=graph-rest-beta) resource",
          "Target": "mobileAppRelationship"
        },
        {
          "Id": "a7e4a6cf-2393-40d7-bf4c-5b8595ec4ad4",
          "ApiChange": "Property",
          "ChangedApiName": "supersededAppCount",
          "ChangeType": "Addition",
          "Description": "Added the **supersededAppCount** property to [mobileApp](/?view=graph-rest-beta) resource",
          "Target": "mobileApp"
        },
        {
          "Id": "a7e4a6cf-2393-40d7-bf4c-5b8595ec4ad4",
          "ApiChange": "Property",
          "ChangedApiName": "supersedingAppCount",
          "ChangeType": "Addition",
          "Description": "Added the **supersedingAppCount** property to [mobileApp](/?view=graph-rest-beta) resource",
          "Target": "mobileApp"
        },
        {
          "Id": "a7e4a6cf-2393-40d7-bf4c-5b8595ec4ad4",
          "ApiChange": "Action",
          "ChangedApiName": "getAppsInstallSummaryReport",
          "ChangeType": "Addition",
          "Description": "Added the [getAppsInstallSummaryReport](/graph/api/intune-getAppsInstallSummaryReport-getAppsInstallSummaryReport?view=graph-rest-beta) method to the [getAppsInstallSummaryReport](/graph/api/intune-getAppsInstallSummaryReport-getAppsInstallSummaryReport?view=graph-rest-beta) resource",
          "Target": "getAppsInstallSummaryReport"
        },
        {
          "Id": "a7e4a6cf-2393-40d7-bf4c-5b8595ec4ad4",
          "ApiChange": "Action",
          "ChangedApiName": "getAppStatusOverviewReport",
          "ChangeType": "Addition",
          "Description": "Added the [getAppStatusOverviewReport](/graph/api/intune-getAppStatusOverviewReport-getAppStatusOverviewReport?view=graph-rest-beta) method to the [getAppStatusOverviewReport](/graph/api/intune-getAppStatusOverviewReport-getAppStatusOverviewReport?view=graph-rest-beta) resource",
          "Target": "getAppStatusOverviewReport"
        },
        {
          "Id": "a7e4a6cf-2393-40d7-bf4c-5b8595ec4ad4",
          "ApiChange": "Action",
          "ChangedApiName": "getDeviceInstallStatusReport",
          "ChangeType": "Addition",
          "Description": "Added the [getDeviceInstallStatusReport](/graph/api/intune-getDeviceInstallStatusReport-getDeviceInstallStatusReport?view=graph-rest-beta) method to the [getDeviceInstallStatusReport](/graph/api/intune-getDeviceInstallStatusReport-getDeviceInstallStatusReport?view=graph-rest-beta) resource",
          "Target": "getDeviceInstallStatusReport"
        },
        {
          "Id": "a7e4a6cf-2393-40d7-bf4c-5b8595ec4ad4",
          "ApiChange": "EntityContainer",
          "ChangedApiName": "edm_50200710",
          "ChangeType": "Deletion",
          "Description": "Removed the **edm_50200710** resource type *@\u0026*",
          "Target": "edm_50200710"
        },
        {
          "Id": "a7e4a6cf-2393-40d7-bf4c-5b8595ec4ad4",
          "ApiChange": "Action",
          "ChangedApiName": "getUserInstallStatusReport",
          "ChangeType": "Addition",
          "Description": "Added the [getUserInstallStatusReport](/graph/api/intune-getUserInstallStatusReport-getUserInstallStatusReport?view=graph-rest-beta) method to the [getUserInstallStatusReport](/graph/api/intune-getUserInstallStatusReport-getUserInstallStatusReport?view=graph-rest-beta) resource",
          "Target": "getUserInstallStatusReport"
        },
        {
          "Id": "a7e4a6cf-2393-40d7-bf4c-5b8595ec4ad4",
          "ApiChange": "EntityContainer",
          "ChangedApiName": "edm_50200902",
          "ChangeType": "Addition",
          "Description": "Added the [edm_50200902](/?view=graph-rest-beta) resource *@\u0026*",
          "Target": "edm_50200902"
        }
      ],
      "Id": "a7e4a6cf-2393-40d7-bf4c-5b8595ec4ad4",
      "Cloud": "Fairfax",
      "Version": "beta",
      "CreatedDateTime": "2020-10-06T16:01:16.3256557Z",
      "WorkloadArea": "Microsoft.Intune.Applications",
      "SubArea": "Corporate management"
    },
    {
      "ChangeList": [
        {
          "Id": "76551c18-d52c-46de-a663-6906472d66d0",
          "ApiChange": "EnumType",
          "ChangedApiName": "mobileAppRelationshipType",
          "ChangeType": "Addition",
          "Description": "Added the [mobileAppRelationshipType](/?view=graph-rest-beta) resource *@\u0026*",
          "Target": "mobileAppRelationshipType"
        },
        {
          "Id": "76551c18-d52c-46de-a663-6906472d66d0",
          "ApiChange": "EntityType",
          "ChangedApiName": "deviceManagement",
          "ChangeType": "Addition",
          "Description": "Added the [deviceManagement](/graph/api/resources/intune-deviceManagement?view=graph-rest-beta) resource *@\u0026*",
          "Target": "deviceManagement"
        },
        {
          "Id": "76551c18-d52c-46de-a663-6906472d66d0",
          "ApiChange": "EnumType",
          "ChangedApiName": "mobileAppSupersedenceType",
          "ChangeType": "Addition",
          "Description": "Added the [mobileAppSupersedenceType](/?view=graph-rest-beta) resource *@\u0026*",
          "Target": "mobileAppSupersedenceType"
        },
        {
          "Id": "76551c18-d52c-46de-a663-6906472d66d0",
          "ApiChange": "EntityType",
          "ChangedApiName": "deviceManagementReports",
          "ChangeType": "Addition",
          "Description": "Added the [deviceManagementReports](/graph/api/resources/intune-deviceManagementReports?view=graph-rest-beta) resource *@\u0026*",
          "Target": "deviceManagementReports"
        },
        {
          "Id": "76551c18-d52c-46de-a663-6906472d66d0",
          "ApiChange": "EntityType",
          "ChangedApiName": "mobileAppSupersedence",
          "ChangeType": "Addition",
          "Description": "Added the [mobileAppSupersedence](/graph/api/resources/intune-mobileAppSupersedence?view=graph-rest-beta) resource *@\u0026*",
          "Target": "mobileAppSupersedence"
        },
        {
          "Id": "76551c18-d52c-46de-a663-6906472d66d0",
          "ApiChange": "Property",
          "ChangedApiName": "installLanguage",
          "ChangeType": "Deletion",
          "Description": "Removed the **installLanguage** property from [win32LobApp](/?view=graph-rest-beta) resource",
          "Target": "win32LobApp"
        },
        {
          "Id": "76551c18-d52c-46de-a663-6906472d66d0",
          "ApiChange": "NavigationProperty",
          "ChangedApiName": "relationships",
          "ChangeType": "Change",
          "Description": "Removed the **relationships** relationship from [mobileApp](/?view=graph-rest-beta) resource",
          "Target": "mobileApp"
        },
        {
          "Id": "76551c18-d52c-46de-a663-6906472d66d0",
          "ApiChange": "Property",
          "ChangedApiName": "targetType",
          "ChangeType": "Addition",
          "Description": "Added the **targetType** property to [mobileAppRelationship](/?view=graph-rest-beta) resource",
          "Target": "mobileAppRelationship"
        },
        {
          "Id": "76551c18-d52c-46de-a663-6906472d66d0",
          "ApiChange": "Property",
          "ChangedApiName": "supersededAppCount",
          "ChangeType": "Addition",
          "Description": "Added the **supersededAppCount** property to [mobileApp](/?view=graph-rest-beta) resource",
          "Target": "mobileApp"
        },
        {
          "Id": "76551c18-d52c-46de-a663-6906472d66d0",
          "ApiChange": "Property",
          "ChangedApiName": "supersedingAppCount",
          "ChangeType": "Addition",
          "Description": "Added the **supersedingAppCount** property to [mobileApp](/?view=graph-rest-beta) resource",
          "Target": "mobileApp"
        },
        {
          "Id": "76551c18-d52c-46de-a663-6906472d66d0",
          "ApiChange": "Action",
          "ChangedApiName": "getAppsInstallSummaryReport",
          "ChangeType": "Addition",
          "Description": "Added the [getAppsInstallSummaryReport](/graph/api/intune-getAppsInstallSummaryReport-getAppsInstallSummaryReport?view=graph-rest-beta) method to the [getAppsInstallSummaryReport](/graph/api/intune-getAppsInstallSummaryReport-getAppsInstallSummaryReport?view=graph-rest-beta) resource",
          "Target": "getAppsInstallSummaryReport"
        },
        {
          "Id": "76551c18-d52c-46de-a663-6906472d66d0",
          "ApiChange": "Action",
          "ChangedApiName": "getAppStatusOverviewReport",
          "ChangeType": "Addition",
          "Description": "Added the [getAppStatusOverviewReport](/graph/api/intune-getAppStatusOverviewReport-getAppStatusOverviewReport?view=graph-rest-beta) method to the [getAppStatusOverviewReport](/graph/api/intune-getAppStatusOverviewReport-getAppStatusOverviewReport?view=graph-rest-beta) resource",
          "Target": "getAppStatusOverviewReport"
        },
        {
          "Id": "76551c18-d52c-46de-a663-6906472d66d0",
          "ApiChange": "Action",
          "ChangedApiName": "getDeviceInstallStatusReport",
          "ChangeType": "Addition",
          "Description": "Added the [getDeviceInstallStatusReport](/graph/api/intune-getDeviceInstallStatusReport-getDeviceInstallStatusReport?view=graph-rest-beta) method to the [getDeviceInstallStatusReport](/graph/api/intune-getDeviceInstallStatusReport-getDeviceInstallStatusReport?view=graph-rest-beta) resource",
          "Target": "getDeviceInstallStatusReport"
        },
        {
          "Id": "76551c18-d52c-46de-a663-6906472d66d0",
          "ApiChange": "Action",
          "ChangedApiName": "getUserInstallStatusReport",
          "ChangeType": "Addition",
          "Description": "Added the [getUserInstallStatusReport](/graph/api/intune-getUserInstallStatusReport-getUserInstallStatusReport?view=graph-rest-beta) method to the [getUserInstallStatusReport](/graph/api/intune-getUserInstallStatusReport-getUserInstallStatusReport?view=graph-rest-beta) resource",
          "Target": "getUserInstallStatusReport"
        },
        {
          "Id": "76551c18-d52c-46de-a663-6906472d66d0",
          "ApiChange": "EntityContainer",
          "ChangedApiName": "edm_50200710",
          "ChangeType": "Deletion",
          "Description": "Removed the **edm_50200710** resource type *@\u0026*",
          "Target": "edm_50200710"
        },
        {
          "Id": "76551c18-d52c-46de-a663-6906472d66d0",
          "ApiChange": "EntityContainer",
          "ChangedApiName": "edm_50200902",
          "ChangeType": "Addition",
          "Description": "Added the [edm_50200902](/?view=graph-rest-beta) resource *@\u0026*",
          "Target": "edm_50200902"
        }
      ],
      "Id": "76551c18-d52c-46de-a663-6906472d66d0",
      "Cloud": "Mooncake",
      "Version": "beta",
      "CreatedDateTime": "2020-10-06T16:01:16.325671Z",
      "WorkloadArea": "Microsoft.Intune.Applications",
      "SubArea": "Corporate management"
    },
    {
      "ChangeList": [
        {
          "Id": "5ee2956e-c2f3-40cf-a08d-0a911a4a5966",
          "ApiChange": "EntityType",
          "ChangedApiName": "deviceManagement",
          "ChangeType": "Addition",
          "Description": "Added the [deviceManagement](/graph/api/resources/intune-deviceManagement?view=graph-rest-beta) resource *@\u0026*",
          "Target": "deviceManagement"
        },
        {
          "Id": "5ee2956e-c2f3-40cf-a08d-0a911a4a5966",
          "ApiChange": "EntityType",
          "ChangedApiName": "deviceManagementReports",
          "ChangeType": "Addition",
          "Description": "Added the [deviceManagementReports](/graph/api/resources/intune-deviceManagementReports?view=graph-rest-beta) resource *@\u0026*",
          "Target": "deviceManagementReports"
        },
        {
          "Id": "5ee2956e-c2f3-40cf-a08d-0a911a4a5966",
          "ApiChange": "EnumType",
          "ChangedApiName": "mobileAppSupersedenceType",
          "ChangeType": "Addition",
          "Description": "Added the [mobileAppSupersedenceType](/?view=graph-rest-beta) resource *@\u0026*",
          "Target": "mobileAppSupersedenceType"
        },
        {
          "Id": "5ee2956e-c2f3-40cf-a08d-0a911a4a5966",
          "ApiChange": "EntityType",
          "ChangedApiName": "mobileAppSupersedence",
          "ChangeType": "Addition",
          "Description": "Added the [mobileAppSupersedence](/graph/api/resources/intune-mobileAppSupersedence?view=graph-rest-beta) resource *@\u0026*",
          "Target": "mobileAppSupersedence"
        },
        {
          "Id": "5ee2956e-c2f3-40cf-a08d-0a911a4a5966",
          "ApiChange": "Property",
          "ChangedApiName": "installLanguage",
          "ChangeType": "Deletion",
          "Description": "Removed the **installLanguage** property from [win32LobApp](/?view=graph-rest-beta) resource",
          "Target": "win32LobApp"
        },
        {
          "Id": "5ee2956e-c2f3-40cf-a08d-0a911a4a5966",
          "ApiChange": "NavigationProperty",
          "ChangedApiName": "relationships",
          "ChangeType": "Change",
          "Description": "Removed the **relationships** relationship from [mobileApp](/?view=graph-rest-beta) resource",
          "Target": "mobileApp"
        },
        {
          "Id": "5ee2956e-c2f3-40cf-a08d-0a911a4a5966",
          "ApiChange": "Property",
          "ChangedApiName": "targetType",
          "ChangeType": "Addition",
          "Description": "Added the **targetType** property to [mobileAppRelationship](/?view=graph-rest-beta) resource",
          "Target": "mobileAppRelationship"
        },
        {
          "Id": "5ee2956e-c2f3-40cf-a08d-0a911a4a5966",
          "ApiChange": "Property",
          "ChangedApiName": "supersededAppCount",
          "ChangeType": "Addition",
          "Description": "Added the **supersededAppCount** property to [mobileApp](/?view=graph-rest-beta) resource",
          "Target": "mobileApp"
        },
        {
          "Id": "5ee2956e-c2f3-40cf-a08d-0a911a4a5966",
          "ApiChange": "Property",
          "ChangedApiName": "supersedingAppCount",
          "ChangeType": "Addition",
          "Description": "Added the **supersedingAppCount** property to [mobileApp](/?view=graph-rest-beta) resource",
          "Target": "mobileApp"
        },
        {
          "Id": "5ee2956e-c2f3-40cf-a08d-0a911a4a5966",
          "ApiChange": "Action",
          "ChangedApiName": "getAppsInstallSummaryReport",
          "ChangeType": "Addition",
          "Description": "Added the [getAppsInstallSummaryReport](/graph/api/intune-getAppsInstallSummaryReport-getAppsInstallSummaryReport?view=graph-rest-beta) method to the [getAppsInstallSummaryReport](/graph/api/intune-getAppsInstallSummaryReport-getAppsInstallSummaryReport?view=graph-rest-beta) resource",
          "Target": "getAppsInstallSummaryReport"
        },
        {
          "Id": "5ee2956e-c2f3-40cf-a08d-0a911a4a5966",
          "ApiChange": "Action",
          "ChangedApiName": "getAppStatusOverviewReport",
          "ChangeType": "Addition",
          "Description": "Added the [getAppStatusOverviewReport](/graph/api/intune-getAppStatusOverviewReport-getAppStatusOverviewReport?view=graph-rest-beta) method to the [getAppStatusOverviewReport](/graph/api/intune-getAppStatusOverviewReport-getAppStatusOverviewReport?view=graph-rest-beta) resource",
          "Target": "getAppStatusOverviewReport"
        },
        {
          "Id": "5ee2956e-c2f3-40cf-a08d-0a911a4a5966",
          "ApiChange": "Action",
          "ChangedApiName": "getDeviceInstallStatusReport",
          "ChangeType": "Addition",
          "Description": "Added the [getDeviceInstallStatusReport](/graph/api/intune-getDeviceInstallStatusReport-getDeviceInstallStatusReport?view=graph-rest-beta) method to the [getDeviceInstallStatusReport](/graph/api/intune-getDeviceInstallStatusReport-getDeviceInstallStatusReport?view=graph-rest-beta) resource",
          "Target": "getDeviceInstallStatusReport"
        },
        {
          "Id": "5ee2956e-c2f3-40cf-a08d-0a911a4a5966",
          "ApiChange": "EntityContainer",
          "ChangedApiName": "edm_50200710",
          "ChangeType": "Deletion",
          "Description": "Removed the **edm_50200710** resource type *@\u0026*",
          "Target": "edm_50200710"
        },
        {
          "Id": "5ee2956e-c2f3-40cf-a08d-0a911a4a5966",
          "ApiChange": "Action",
          "ChangedApiName": "getUserInstallStatusReport",
          "ChangeType": "Addition",
          "Description": "Added the [getUserInstallStatusReport](/graph/api/intune-getUserInstallStatusReport-getUserInstallStatusReport?view=graph-rest-beta) method to the [getUserInstallStatusReport](/graph/api/intune-getUserInstallStatusReport-getUserInstallStatusReport?view=graph-rest-beta) resource",
          "Target": "getUserInstallStatusReport"
        },
        {
          "Id": "5ee2956e-c2f3-40cf-a08d-0a911a4a5966",
          "ApiChange": "EntityContainer",
          "ChangedApiName": "edm_50200902",
          "ChangeType": "Addition",
          "Description": "Added the [edm_50200902](/?view=graph-rest-beta) resource *@\u0026*",
          "Target": "edm_50200902"
        }
      ],
      "Id": "5ee2956e-c2f3-40cf-a08d-0a911a4a5966",
      "Cloud": "Prod",
      "Version": "beta",
      "CreatedDateTime": "2020-10-06T16:01:16.3256875Z",
      "WorkloadArea": "Microsoft.Intune.Applications",
      "SubArea": "Corporate management"
    },
    {
      "ChangeList": [
        {
          "Id": "8a0cf876-4a45-427e-9cfb-3c898d8fbbb7",
          "ApiChange": "EnumType",
          "ChangedApiName": "runAsAccountType",
          "ChangeType": "Addition",
          "Description": "Added the [runAsAccountType](/?view=graph-rest-1.0) resource *@\u0026*",
          "Target": "runAsAccountType"
        },
        {
          "Id": "8a0cf876-4a45-427e-9cfb-3c898d8fbbb7",
          "ApiChange": "EnumType",
          "ChangedApiName": "win32LobAppNotification",
          "ChangeType": "Addition",
          "Description": "Added the [win32LobAppNotification](/?view=graph-rest-1.0) resource *@\u0026*",
          "Target": "win32LobAppNotification"
        },
        {
          "Id": "8a0cf876-4a45-427e-9cfb-3c898d8fbbb7",
          "ApiChange": "EnumType",
          "ChangedApiName": "win32LobAppMsiPackageType",
          "ChangeType": "Addition",
          "Description": "Added the [win32LobAppMsiPackageType](/?view=graph-rest-1.0) resource *@\u0026*",
          "Target": "win32LobAppMsiPackageType"
        },
        {
          "Id": "8a0cf876-4a45-427e-9cfb-3c898d8fbbb7",
          "ApiChange": "EnumType",
          "ChangedApiName": "win32LobAppPowerShellScriptRuleOperationType",
          "ChangeType": "Addition",
          "Description": "Added the [win32LobAppPowerShellScriptRuleOperationType](/?view=graph-rest-1.0) resource *@\u0026*",
          "Target": "win32LobAppPowerShellScriptRuleOperationType"
        },
        {
          "Id": "8a0cf876-4a45-427e-9cfb-3c898d8fbbb7",
          "ApiChange": "EnumType",
          "ChangedApiName": "win32LobAppRegistryRuleOperationType",
          "ChangeType": "Addition",
          "Description": "Added the [win32LobAppRegistryRuleOperationType](/?view=graph-rest-1.0) resource *@\u0026*",
          "Target": "win32LobAppRegistryRuleOperationType"
        },
        {
          "Id": "8a0cf876-4a45-427e-9cfb-3c898d8fbbb7",
          "ApiChange": "ComplexType",
          "ChangedApiName": "win32LobAppFileSystemRule",
          "ChangeType": "Addition",
          "Description": "Added the [win32LobAppFileSystemRule](/graph/api/resources/intune-win32LobAppFileSystemRule?view=graph-rest-1.0) resource type",
          "Target": "win32LobAppFileSystemRule"
        },
        {
          "Id": "8a0cf876-4a45-427e-9cfb-3c898d8fbbb7",
          "ApiChange": "ComplexType",
          "ChangedApiName": "win32LobAppInstallExperience",
          "ChangeType": "Addition",
          "Description": "Added the [win32LobAppInstallExperience](/graph/api/resources/intune-win32LobAppInstallExperience?view=graph-rest-1.0) resource type",
          "Target": "win32LobAppInstallExperience"
        },
        {
          "Id": "8a0cf876-4a45-427e-9cfb-3c898d8fbbb7",
          "ApiChange": "ComplexType",
          "ChangedApiName": "win32LobAppMsiInformation",
          "ChangeType": "Addition",
          "Description": "Added the [win32LobAppMsiInformation](/graph/api/resources/intune-win32LobAppMsiInformation?view=graph-rest-1.0) resource type",
          "Target": "win32LobAppMsiInformation"
        },
        {
          "Id": "8a0cf876-4a45-427e-9cfb-3c898d8fbbb7",
          "ApiChange": "EnumType",
          "ChangedApiName": "win32LobAppRuleType",
          "ChangeType": "Addition",
          "Description": "Added the [win32LobAppRuleType](/?view=graph-rest-1.0) resource *@\u0026*",
          "Target": "win32LobAppRuleType"
        },
        {
          "Id": "8a0cf876-4a45-427e-9cfb-3c898d8fbbb7",
          "ApiChange": "ComplexType",
          "ChangedApiName": "mobileAppInstallTimeSettings",
          "ChangeType": "Addition",
          "Description": "Added the [mobileAppInstallTimeSettings](/graph/api/resources/intune-mobileAppInstallTimeSettings?view=graph-rest-1.0) resource type",
          "Target": "mobileAppInstallTimeSettings"
        },
        {
          "Id": "8a0cf876-4a45-427e-9cfb-3c898d8fbbb7",
          "ApiChange": "ComplexType",
          "ChangedApiName": "win32LobAppAssignmentSettings",
          "ChangeType": "Addition",
          "Description": "Added the [win32LobAppAssignmentSettings](/graph/api/resources/intune-win32LobAppAssignmentSettings?view=graph-rest-1.0) resource type",
          "Target": "win32LobAppAssignmentSettings"
        },
        {
          "Id": "8a0cf876-4a45-427e-9cfb-3c898d8fbbb7",
          "ApiChange": "EnumType",
          "ChangedApiName": "win32LobAppRestartBehavior",
          "ChangeType": "Addition",
          "Description": "Added the [win32LobAppRestartBehavior](/?view=graph-rest-1.0) resource *@\u0026*",
          "Target": "win32LobAppRestartBehavior"
        },
        {
          "Id": "8a0cf876-4a45-427e-9cfb-3c898d8fbbb7",
          "ApiChange": "EnumType",
          "ChangedApiName": "win32LobAppReturnCodeType",
          "ChangeType": "Addition",
          "Description": "Added the [win32LobAppReturnCodeType](/?view=graph-rest-1.0) resource *@\u0026*",
          "Target": "win32LobAppReturnCodeType"
        },
        {
          "Id": "8a0cf876-4a45-427e-9cfb-3c898d8fbbb7",
          "ApiChange": "EnumType",
          "ChangedApiName": "win32LobAppRuleOperator",
          "ChangeType": "Addition",
          "Description": "Added the [win32LobAppRuleOperator](/?view=graph-rest-1.0) resource *@\u0026*",
          "Target": "win32LobAppRuleOperator"
        },
        {
          "Id": "8a0cf876-4a45-427e-9cfb-3c898d8fbbb7",
          "ApiChange": "ComplexType",
          "ChangedApiName": "win32LobAppPowerShellScriptRule",
          "ChangeType": "Addition",
          "Description": "Added the [win32LobAppPowerShellScriptRule](/graph/api/resources/intune-win32LobAppPowerShellScriptRule?view=graph-rest-1.0) resource type",
          "Target": "win32LobAppPowerShellScriptRule"
        },
        {
          "Id": "8a0cf876-4a45-427e-9cfb-3c898d8fbbb7",
          "ApiChange": "ComplexType",
          "ChangedApiName": "win32LobAppProductCodeRule",
          "ChangeType": "Addition",
          "Description": "Added the [win32LobAppProductCodeRule](/graph/api/resources/intune-win32LobAppProductCodeRule?view=graph-rest-1.0) resource type",
          "Target": "win32LobAppProductCodeRule"
        },
        {
          "Id": "8a0cf876-4a45-427e-9cfb-3c898d8fbbb7",
          "ApiChange": "ComplexType",
          "ChangedApiName": "win32LobAppRegistryRule",
          "ChangeType": "Addition",
          "Description": "Added the [win32LobAppRegistryRule](/graph/api/resources/intune-win32LobAppRegistryRule?view=graph-rest-1.0) resource type",
          "Target": "win32LobAppRegistryRule"
        },
        {
          "Id": "8a0cf876-4a45-427e-9cfb-3c898d8fbbb7",
          "ApiChange": "ComplexType",
          "ChangedApiName": "win32LobAppRule",
          "ChangeType": "Addition",
          "Description": "Added the [win32LobAppRule](/graph/api/resources/intune-win32LobAppRule?view=graph-rest-1.0) resource type",
          "Target": "win32LobAppRule"
        },
        {
          "Id": "8a0cf876-4a45-427e-9cfb-3c898d8fbbb7",
          "ApiChange": "ComplexType",
          "ChangedApiName": "win32LobAppRestartSettings",
          "ChangeType": "Addition",
          "Description": "Added the [win32LobAppRestartSettings](/graph/api/resources/intune-win32LobAppRestartSettings?view=graph-rest-1.0) resource type",
          "Target": "win32LobAppRestartSettings"
        },
        {
          "Id": "8a0cf876-4a45-427e-9cfb-3c898d8fbbb7",
          "ApiChange": "ComplexType",
          "ChangedApiName": "win32LobAppReturnCode",
          "ChangeType": "Addition",
          "Description": "Added the [win32LobAppReturnCode](/graph/api/resources/intune-win32LobAppReturnCode?view=graph-rest-1.0) resource type",
          "Target": "win32LobAppReturnCode"
        }
      ],
      "Id": "8a0cf876-4a45-427e-9cfb-3c898d8fbbb7",
      "Cloud": "Prod",
      "Version": "v1.0",
      "CreatedDateTime": "2020-10-06T16:01:16.3257037Z",
      "WorkloadArea": "Microsoft.Intune.Applications",
      "SubArea": "Corporate management"
    }
  ]
}